brandub/__init__.py
brandub/board.py
brandub/brandubgame.py
brandub/errors.py
brandub/gamehistory.py
brandub/gamestate.py
brandub/movement.py
brandub/rawboard.py
brandub/valid_moves.py
brandub-1.0.1.data/scripts/brandub
brandub-1.0.1.dist-info/LICENSE
brandub-1.0.1.dist-info/METADATA
brandub-1.0.1.dist-info/WHEEL
brandub-1.0.1.dist-info/top_level.txt
brandub-1.0.1.dist-info/RECORD
