Metadata-Version: 2.1
Name: brandub
Version: 1.0.1
Summary: play brandub
Home-page: https://github.com/kevinnowland/brandub
Author: Kevin Nowland
License: MIT
Platform: UNKNOWN
Requires-Dist: ipython
Requires-Dist: numpy
